creds_to_env/__init__.py
creds_to_env/__main__.py
creds_to_env-1.0.0.dist-info/LICENSE
creds_to_env-1.0.0.dist-info/METADATA
creds_to_env-1.0.0.dist-info/WHEEL
creds_to_env-1.0.0.dist-info/entry_points.txt
creds_to_env-1.0.0.dist-info/top_level.txt
creds_to_env-1.0.0.dist-info/RECORD
