Metadata-Version: 2.1
Name: creds-to-env
Version: 1.0.0
Summary: Maps AWS Credentials to Docker Environment File
Home-page: https://github.com/scottoffen/creds-to-env
Author: Scott Offen
Author-email: 3513626+scottoffen@users.noreply.github.com
License: UNKNOWN
Project-URL: Bug Reports, https://github.com/scottoffen/creds-to-env/issues
Project-URL: Source, https://github.com/scottoffen/creds-to-env/
Keywords: aws credentials creds docker
Platform: UNKNOWN
Classifier: Development Status :: 5 - Production/Stable
Classifier: Intended Audience :: Developers
Classifier: Topic :: Software Development :: Build Tools
Classifier: License :: OSI Approved :: MIT License
Classifier: Programming Language :: Python :: 3
Classifier: Programming Language :: Python :: 3.6
Classifier: Programming Language :: Python :: 3.7
Classifier: Programming Language :: Python :: 3.8
Classifier: Programming Language :: Python :: 3.9
Classifier: Programming Language :: Python :: 3.10
Classifier: Programming Language :: Python :: 3 :: Only
Classifier: Operating System :: OS Independent
Requires-Python: >=3.6, <4
License-File: LICENSE
